MANIFEST.in
requirements.txt
setup.py
./require/__init__.py
./require/__main__.py
./require/config.py
./require/decorators.py
./require/main.py
./require/python.py
./require/require.py
./require/run.py
./require/setup.py
stack_require.egg-info/PKG-INFO
stack_require.egg-info/SOURCES.txt
stack_require.egg-info/dependency_links.txt
stack_require.egg-info/entry_points.txt
stack_require.egg-info/requires.txt
stack_require.egg-info/top_level.txt