Metadata-Version: 1.1
Name: stack-require
Version: 0.0.2.1
Summary: `require` is a part of `stack` project
Home-page: http://python-stack.readthedocs.io
Author: Ryan Kung
Author-email: ryankung@ieee.org
License: MIT
Platform: UNKNOWN
Classifier: Development Status :: 4 - Beta
Classifier: Environment :: Console
Classifier: Programming Language :: Python :: 3.5
Classifier: Operating System :: OS Independent
Classifier: Topic :: Software Development
Classifier: Topic :: Software Development :: Libraries :: Python Modules
